{
    "ExampleTopKey": "ExampleTopValue",
    "TotalNumberOfLitterPicks": 100,
    "MostLitterFoundInBoundary": "1",
    "Boundary": [
        {
            "id": "1",
            "Name": "NorthEastLincolnshire",
            "CollectedLitterLiters": 10.5,
            "PickHistory": [
                {
                    "DateTime": "2024-07-14T15:47:35.995Z",
                    "SiteId": "1824",
                    "WardId": "15"
                }
            ],
            "TotalPicks": 1,
            "SiteHistory": [
                {
                    "SiteId": "1824",
                    "PickCount": 1,
                    "BagsFull": 2.75
                }
            ],
            "WardHistory": [
                {
                    "WardId": "15",
                    "PickCount": 1
                }
            ],
            "TopSite": 1260,
            "TopWard": 15,
            "ReportHistory": [
                {
                    "ObjectType": "Balloon",
                    "DateTime": "DT VALUE"
                },
                {
                    "ObjectType": "Trolley",
                    "DateTime": "DT VALUE"
                }
            ],
            "BalloonCount": 1,
            "TrolleyCount": 1
        }
    ]
}
